setup.py
CASutils/CASutils.py
CASutils/__init__.py
CASutils.egg-info/PKG-INFO
CASutils.egg-info/SOURCES.txt
CASutils.egg-info/dependency_links.txt
CASutils.egg-info/requires.txt
CASutils.egg-info/top_level.txt
bin/CASutils_runner