Metadata-Version: 1.0
Name: CASutils
Version: 0.191111
Summary: Just some utilities I find useful for my research
Home-page: http://pypi.python.org/pypi/CASutils/
Author: Craig Snoeyink
Author-email: craig.snoeyink@gmail.com
License: UNKNOWN
Platform: UNKNOWN
